MANIFEST.in
README.md
setup.py
marsha/__init__.py
marsha/format_registry.py
marsha/object.py
marsha/types.py
marsha.egg-info/PKG-INFO
marsha.egg-info/SOURCES.txt
marsha.egg-info/dependency_links.txt
marsha.egg-info/top_level.txt
marsha/formats/__init__.py
marsha/formats/any.py
marsha/formats/base_format.py
marsha/formats/callable.py
marsha/formats/date_string.py
marsha/formats/decimal.py
marsha/formats/decimal_string.py
marsha/formats/dict.py
marsha/formats/float.py
marsha/formats/integer.py
marsha/formats/integer_string.py
marsha/formats/list.py
marsha/formats/none_type.py
marsha/formats/object.py
marsha/formats/raw_format.py
marsha/formats/string.py
marsha/formats/union.py