Metadata-Version: 2.1
Name: marsha
Version: 0.2.3
Summary: UNKNOWN
Home-page: https://gitlab.com/deckar01/marsha
Author: Jared Deckard
Author-email: jared@shademaps.com
License: MIT
Platform: UNKNOWN
